lirayspy/__init__.py
lirayspy/client.py
lirayspy/tools.py
lirayspy-0.0.4.dist-info/licenses/LICENSE
lirayspy-0.0.4.dist-info/METADATA
lirayspy-0.0.4.dist-info/WHEEL
lirayspy-0.0.4.dist-info/top_level.txt
lirayspy-0.0.4.dist-info/RECORD
