Metadata-Version: 2.4
Name: lirayspy
Version: 0.0.4
Summary: Python client library for LiRAYS API - Fiber Network Design
Author-email: LiRAYS API Client <support@lirays.com>
Project-URL: Homepage, https://github.com/LiRAYSgj/Lirays-Api-Python-Client
Project-URL: Documentation, https://github.com/LiRAYSgj/Lirays-Api-Python-Client#readme
Project-URL: Repository, https://github.com/LiRAYSgj/Lirays-Api-Python-Client
Project-URL: Bug Tracker, https://github.com/LiRAYSgj/Lirays-Api-Python-Client/issues
Keywords: lirays,api,gis,fiber,network,design
Requires-Python: >=3.8
License-File: LICENSE
Requires-Dist: httpx>=0.24.0
Requires-Dist: requests>=2.31.0
Requires-Dist: pydantic>=2.0.0
Requires-Dist: python-dateutil>=2.8.0
Requires-Dist: typing-extensions>=4.0.0; python_version < "3.10"
Provides-Extra: dev
Requires-Dist: pytest>=7.0.0; extra == "dev"
Requires-Dist: pytest-asyncio>=0.21.0; extra == "dev"
Requires-Dist: pytest-httpx>=0.21.0; extra == "dev"
Requires-Dist: black>=23.0.0; extra == "dev"
Requires-Dist: isort>=5.12.0; extra == "dev"
Requires-Dist: mypy>=1.0.0; extra == "dev"
Requires-Dist: pre-commit>=3.0.0; extra == "dev"
Dynamic: license-file
